dangling_finder/__init__.py
dangling_finder/__main__.py
dangling_finder/exceptions.py
dangling_finder/listing.py
dangling_finder/main.py
dangling_finder/output.py
dangling_finder-0.3.3.dist-info/LICENSE
dangling_finder-0.3.3.dist-info/METADATA
dangling_finder-0.3.3.dist-info/WHEEL
dangling_finder-0.3.3.dist-info/entry_points.txt
dangling_finder-0.3.3.dist-info/RECORD
