Metadata-Version: 2.1
Name: dangling-finder
Version: 0.3.3
Summary: 
License: MIT
Author: Mickaël Fontès
Author-email: 81414455+MickaelFontes@users.noreply.github.com
Requires-Python: >=3.10,<4.0
Classifier: License :: OSI Approved :: MIT License
Classifier: Programming Language :: Python :: 3
Classifier: Programming Language :: Python :: 3.10
Classifier: Programming Language :: Python :: 3.11
Classifier: Programming Language :: Python :: 3.12
Requires-Dist: requests (>=2.31.0,<3.0.0)
Requires-Dist: typer[all] (>=0.9.0,<0.10.0)
